rackspace/__init__.py
rackspace/connection.py
rackspace/profile.py
rackspace/auth/__init__.py
rackspace/auth/identity/__init__.py
rackspace/auth/identity/rackspace.py
rackspace/backup/__init__.py
rackspace/backup/backup_service.py
rackspace/backup/v1/__init__.py
rackspace/backup/v1/_proxy.py
rackspace/backup/v1/activity.py
rackspace/backup/v1/agent.py
rackspace/backup/v1/backup_configuration.py
rackspace/backup/v1/restore_configuration.py
rackspace/database/__init__.py
rackspace/database/database_service.py
rackspace/database/v1/__init__.py
rackspace/database/v1/_proxy.py
rackspace/database/v1/backup.py
rackspace/database/v1/backup_schedule.py
rackspace/database/v1/configuration.py
rackspace/database/v1/high_availability_instance.py
rackspace/load_balancer/__init__.py
rackspace/load_balancer/load_balancer_service.py
rackspace/load_balancer/v1/__init__.py
rackspace/load_balancer/v1/_proxy.py
rackspace/load_balancer/v1/load_balancer.py
rackspace/load_balancer/v1/ssl_termination.py
rackspace/message/__init__.py
rackspace/message/message_service.py
rackspace/message/v1/__init__.py
rackspace/message/v1/_proxy.py
rackspace/monitoring/__init__.py
rackspace/monitoring/monitoring_service.py
rackspace/monitoring/v1/__init__.py
rackspace/monitoring/v1/_proxy.py
rackspace/monitoring/v1/agent.py
rackspace/monitoring/v1/agent_token.py
rackspace/monitoring/v1/alarm.py
rackspace/monitoring/v1/check.py
rackspace/monitoring/v1/check_type.py
rackspace/monitoring/v1/entity.py
rackspace/monitoring/v1/monitoring_zone.py
rackspace/monitoring/v1/notification.py
rackspace/monitoring/v1/notification_plan.py
rackspace/monitoring/v1/notification_type.py
rackspace/monitoring/v1/overview.py
rackspace/monitoring/v1/suppression.py
rackspace/monitoring/v1/suppression_log.py
rackspace/object_store/__init__.py
rackspace/object_store/object_store_service.py
rackspace/object_store/v1/__init__.py
rackspace/object_store/v1/_proxy.py
rackspacesdk-0.7.5.dist-info/DESCRIPTION.rst
rackspacesdk-0.7.5.dist-info/METADATA
rackspacesdk-0.7.5.dist-info/RECORD
rackspacesdk-0.7.5.dist-info/WHEEL
rackspacesdk-0.7.5.dist-info/entry_points.txt
rackspacesdk-0.7.5.dist-info/metadata.json
rackspacesdk-0.7.5.dist-info/pbr.json
rackspacesdk-0.7.5.dist-info/top_level.txt
